{"name":"IC3657","id":3657,"images":[{"filename":"ic_3657_default.jpg","description":"SDSS image of lenticular galaxy IC 3657","origin_url":"https://cseligman.com/text/atlas/ic36a.htm#ic3657","is_default":true},{"filename":"ic3657comp.jpg","description":"SDSS image comparing lenticular galaxy IC 3657 to two stars","origin_url":"https://cseligman.com/text/atlas/ic36a.htm#ic3657"},{"filename":"ic3657wide.jpg","description":"SDSS image of region near lenticular galaxy IC 3657","origin_url":"https://cseligman.com/text/atlas/ic36a.htm#ic3657"},{"is_default":false,"filename":"ic_3657_ae18ad10-1871-4121-b1c6-91fc75ec97df.jpg"},{"is_default":false,"filename":"ic_3657_0b885f49-4d9c-4e36-8a5a-6c54413a37ca.jpg"}]}