{"name":"IC382","id":382,"images":[{"filename":"ic_382_default.jpg","description":"DSS image of region near spiral galaxy IC 382, which is sometimes misidentified as NGC 1632","origin_url":"https://cseligman.com/text/atlas/ic3a.htm#ic382","is_default":true},{"filename":"ic382.jpg","description":"DSS image of spiral galaxy IC 382, which is sometimes misidentified as NGC 1632","origin_url":"https://cseligman.com/text/atlas/ic3a.htm#ic382"},{"filename":"ic382pstarrs.jpg","description":"PanSTARRS image of spiral galaxy IC 382, which is sometimes misidentified as NGC 1632","origin_url":"https://cseligman.com/text/atlas/ic3a.htm#ic382"},{"is_default":false,"filename":"ic_382_c493548a-3639-4ba0-b191-523965461d9d.jpg"},{"is_default":false,"filename":"ic_382_3f00336c-6faa-4f6f-9d26-8e087c1a1ab4.jpg"}]}