{"name":"IC392","id":392,"images":[{"filename":"ic_392_default.jpg","description":"DSS image of region near spiral galaxy IC 392","origin_url":"https://cseligman.com/text/atlas/ic3a.htm#ic392","is_default":true},{"filename":"ic_392_09be34ea-bd97-4aba-94be-d44610983234.jpg","description":"DSS image of spiral galaxy IC 392","origin_url":"https://cseligman.com/text/atlas/ic3a.htm#ic392","is_default":false},{"filename":"ic_392_d79535da-2845-4a64-bccf-cf9e3ba4169d.jpg","description":"PanSTARRS image of spiral galaxy IC 392","origin_url":"https://cseligman.com/text/atlas/ic3a.htm#ic392","is_default":false}]}