{"name":"IC4998","id":4998,"images":[{"filename":"ic_4998_default.jpg","description":"DSS image of region near Swift's position for the probably lost or nonexistent IC 4998","origin_url":"https://cseligman.com/text/atlas/ic49a.htm#ic4998","is_default":true},{"filename":"ic_4998_4e778fe7-3dca-482f-91b3-0cfc63154b09.jpg","description":"DSS image of region near spiral galaxy PGC 64546, which is often (mis)identified as IC 4998","origin_url":"https://cseligman.com/text/atlas/ic49a.htm#ic4998","is_default":false},{"filename":"ic_4998_2dcac9ef-317b-48e5-a34b-4926e3a6e5af.jpg","description":"DSS image of spiral galaxy PGC 64546, which is often (mis)identified as IC 4998","origin_url":"https://cseligman.com/text/atlas/ic49a.htm#ic4998","is_default":false}]}