{"name":"IC60","id":60,"images":[{"filename":"ic_60_default.jpg","description":"DSS image of region near lenticular galaxy IC 60","origin_url":"https://cseligman.com/text/atlas/ic0a.htm#ic60","is_default":true},{"filename":"ic60.jpg","description":"DSS image of lenticular galaxy IC 60","origin_url":"https://cseligman.com/text/atlas/ic0a.htm#ic60"},{"filename":"ic60pstarrs.jpg","description":"PanSTARRS image of lenticular galaxy IC 60","origin_url":"https://cseligman.com/text/atlas/ic0a.htm#ic60"},{"is_default":false,"filename":"ic_60_774fc4a0-9a80-4a38-8084-5bd5ce9d0b20.jpg"},{"is_default":false,"filename":"ic_60_fd0bfb6d-0158-4146-b5af-4eded43223d2.jpg"}]}