{"name":"NGC3040","id":3040,"images":[{"filename":"ngc_3040_default.jpg","description":"SDSS image of region near lenticular galaxy NGC 3040","origin_url":"https://cseligman.com/text/atlas/ngc30.htm#3040","is_default":true},{"filename":"ngc3040.jpg","description":"SDSS image of region near lenticular galaxy NGC 3040, also showing part of PGC 200525","origin_url":"https://cseligman.com/text/atlas/ngc30.htm#3040"},{"filename":"ngc3040widepgc.jpg","description":"SDSS image of region near lenticular galaxy NGC 3040, also showing PGC 200252, PGC 1591421 and PGC 28480","origin_url":"https://cseligman.com/text/atlas/ngc30.htm#3040"},{"filename":"pgc200252.jpg","description":"SDSS image of spiral galaxy PGC 200252, which is sometimes mislabeled as NGC 3040B","origin_url":"https://cseligman.com/text/atlas/ngc30.htm#3040"},{"is_default":false,"filename":"ngc_3040_a5ec6e1f-7685-4958-996c-bb130c7a6092.jpg"},{"is_default":false,"filename":"ngc_3040_7fbf4de0-1e27-4872-9578-aaaee5e8aaf9.jpg"},{"is_default":false,"filename":"ngc_3040_f319ed60-385b-4b57-822f-8dbd3de7da23.jpg"}]}