{"name":"NGC6608","id":6608,"images":[{"filename":"ngc_6608_default.jpg","description":"DSS image of lenticular galaxy PGC 61556, which is often misidentified as NGC 6608 or NGC 6609","origin_url":"https://cseligman.com/text/atlas/ngc66.htm#6608","is_default":true},{"filename":"pgc61556pstarrs.jpg","description":"PanSTARRS image of lenticular galaxy PGC 61556, which is often misidentified as NGC 6608 or NGC 6609","origin_url":"https://cseligman.com/text/atlas/ngc66.htm#6608"},{"is_default":false,"filename":"ngc_6608_61668338-c493-4ec5-930d-42db3f7cc129.jpg"}]}