{"name":"NGC4254","id":4254,"images":[{"filename":"ngc_4254_default.jpg","description":"SDSS image of region near spiral galaxy NGC 4254, also known as M99","origin_url":"https://cseligman.com/text/atlas/ngc42a.htm#4254","is_default":true},{"filename":"ngc_4254_691f356c-0b32-4eee-b5e6-473289702a14.jpg","description":"SDSS image of spiral galaxy NGC 4254, also known as M99","origin_url":"https://cseligman.com/text/atlas/ngc42a.htm#4254","is_default":false},{"filename":"ngc_4254_961dbb9e-3fb0-469f-9ac7-402263ea9687.jpg","description":"NOAO image of spiral galaxy NGC 4254, also known as M99","origin_url":"https://cseligman.com/text/atlas/ngc42a.htm#4254","is_default":false}]}