{"name":"NGC3311","id":3311,"images":[{"filename":"ngc_3311_default.jpg","description":"DSS image of region near elliptical galaxy NGC 3311, also showing NGC 3307, NGC 3308, NGC 3309 and NGC 3312","origin_url":"https://cseligman.com/text/atlas/ngc33.htm#3311","is_default":true},{"filename":"ngc_3311_6a67009c-ec80-4cf7-8a38-c9f9358a9c52.jpg","description":"Carnegie-Irvine Galaxy Survey image of elliptical galaxy NGC 3311","origin_url":"https://cseligman.com/text/atlas/ngc33.htm#3311","is_default":false}]}