{"name":"NGC7196","id":7196,"images":[{"filename":"ngc_7196_default.jpg","description":"DSS image of region near elliptical galaxy NGC 7196, also showing PGC 129874","origin_url":"https://cseligman.com/text/atlas/ngc71a.htm#7196","is_default":true},{"filename":"ngc7196.jpg","description":"Carnegie-Irvine Galaxy Survey image of elliptical galaxy NGC 7196","origin_url":"https://cseligman.com/text/atlas/ngc71a.htm#7196"},{"filename":"ngc7196wide.jpg","description":"DSS image of region near elliptical galaxy NGC 7196, also showing PGC 129874","origin_url":"https://cseligman.com/text/atlas/ngc71a.htm#7196"},{"filename":"ngc7196.jpg","description":"Carnegie-Irvine Galaxy Survey image of elliptical galaxy NGC 7196","origin_url":"https://cseligman.com/text/atlas/ngc71a.htm#7196"},{"is_default":false,"filename":"ngc_7196_4cad09d9-67b7-47a4-92d2-7d63dbdd220e.jpg"}]}