{"name":"NGC241","id":241,"images":[{"filename":"ngc_241_default.jpg","description":"DSS image of region near NGC 241, an open cluster in the Small Magellanic Cloud","origin_url":"https://cseligman.com/text/atlas/ngc2.htm#241","is_default":true},{"filename":"ngc241.jpg","description":"DSS image of NGC 241, an open cluster in the Small Magellanic Cloud","origin_url":"https://cseligman.com/text/atlas/ngc2.htm#241"},{"is_default":false,"filename":"ngc_241_7e1986b9-8463-46e0-a82c-4ee86b82b851.jpg"}]}