{"name":"NGC2901","id":2901,"images":[{"filename":"ngc_2901_default.jpg","description":"SDSS image of region near the NGC position of the apparently lost or nonexistent NGC 2901","origin_url":"https://cseligman.com/text/atlas/ngc29.htm#2901","is_default":true},{"filename":"pgc27023wide.jpg","description":"SDSS image of region near spiral galaxy PGC 27023, which may sometimes be misidentified as NGC 2901","origin_url":"https://cseligman.com/text/atlas/ngc29.htm#2901"},{"filename":"pgc27023.jpg","description":"SDSS image of spiral galaxy PGC 27023, which may sometimes be misidentified as NGC 2901","origin_url":"https://cseligman.com/text/atlas/ngc29.htm#2901"},{"is_default":false,"filename":"ngc_2901_7ae0b480-b958-4804-bc19-c1c675b01895.jpg"},{"is_default":false,"filename":"ngc_2901_3123b141-a3b5-49e9-85e6-08de34a2f4df.jpg"}]}