{"name":"NGC4030","id":4030,"images":[{"filename":"ngc_4030_default.jpg","description":"SDSS image of region near spiral galaxy NGC 4030","origin_url":"https://cseligman.com/text/atlas/ngc40.htm#4030","is_default":true},{"filename":"ngc_4030_c59ab48f-9cdc-4ccb-a40e-ac12460ac5a8.jpg","description":"SDSS image of spiral galaxy NGC 4030","origin_url":"https://cseligman.com/text/atlas/ngc40.htm#4030","is_default":false},{"filename":"ngc_4030_d1d69832-5196-4387-8c3e-1ec18d437104.jpg","description":"Carnegie-Irvine Galaxy Survey image of spiral galaxy NGC 4030","origin_url":"https://cseligman.com/text/atlas/ngc40.htm#4030","is_default":false},{"filename":"ngc_4030_7d8c9101-9092-43a1-857f-9203ad300156.jpg","description":"ESO infrared image of spiral galaxy NGC 4030","origin_url":"https://cseligman.com/text/atlas/ngc40.htm#4030","is_default":false},{"filename":"ngc_4030_81615f08-9e3f-424f-a8ae-9c614c7cc4b6.jpg","description":"HST image of spiral galaxy NGC 4030","origin_url":"https://cseligman.com/text/atlas/ngc40.htm#4030","is_default":false}]}