{"name":"NGC4411","id":4411,"images":[{"filename":"ngc_4411_default.jpg","description":"SDSS image of spiral galaxy NGC 4411, also showing the star listed as IC 3343","origin_url":"https://cseligman.com/text/atlas/ngc44.htm#4411","is_default":true},{"filename":"ngc_4411_5ebf5794-5732-479e-9b8d-f0db67d5171a.jpg","description":"SDSS image of region near spiral galaxy NGC 4411, also showing the star listed as IC 3343 and spiral galaxy PGC 40745, which is also known as NGC 4411B","origin_url":"https://cseligman.com/text/atlas/ngc44.htm#4411","is_default":false},{"filename":"ngc_4411_504043be-3e4c-441a-96b7-2a673babc764.jpg","description":"SDSS image of spiral galaxy PGC 40745, also known as NGC 4411B","origin_url":"https://cseligman.com/text/atlas/ngc44.htm#4411","is_default":false},{"filename":"ngc_4411_8280c6b4-205c-47f4-8466-a7da6329f883.jpg","description":"SDSS image of spiral galaxy PGC 40745, also known as NGC 4411B; also shown are spiral galaxy NGC 4411 and the star listed as IC 3343","origin_url":"https://cseligman.com/text/atlas/ngc44.htm#4411","is_default":false}]}