{"name":"NGC3107","id":3107,"images":[{"filename":"ngc_3107_default.jpg","description":"SDSS image of region near Dreyer's position for NGC 3107","origin_url":"https://cseligman.com/text/atlas/ngc31.htm#3107","is_default":true},{"filename":"ngc3107wide.jpg","description":"SDSS image of region near spiral galaxy NGC 3107","origin_url":"https://cseligman.com/text/atlas/ngc31.htm#3107"},{"filename":"ngc3107.jpg","description":"SDSS image of spiral galaxy NGC 3107","origin_url":"https://cseligman.com/text/atlas/ngc31.htm#3107"},{"is_default":false,"filename":"ngc_3107_8da7fce6-f0fd-4e66-829f-0358d2869286.jpg"},{"is_default":false,"filename":"ngc_3107_379797a0-bd8a-478b-9869-44b9ca408893.jpg"}]}