{"name":"NGC6569","id":6569,"images":[{"filename":"ngc_6569_default.jpg","description":"DSS image of region near globular cluster NGC 6569","origin_url":"https://cseligman.com/text/atlas/ngc65a.htm#6569","is_default":true},{"filename":"ngc6569.jpg","description":"DSS image of globular cluster NGC 6569","origin_url":"https://cseligman.com/text/atlas/ngc65a.htm#6569"},{"filename":"ngc6569hst.jpg","description":"HST image of globular cluster NGC 6569","origin_url":"https://cseligman.com/text/atlas/ngc65a.htm#6569"},{"filename":"ngc6569hst2.jpg","description":"HST image of globular cluster NGC 6569","origin_url":"https://cseligman.com/text/atlas/ngc65a.htm#6569"},{"is_default":false,"filename":"ngc_6569_ed68b6d1-678c-49e9-a20a-e7d80bb26966.jpg"},{"is_default":false,"filename":"ngc_6569_622cf06d-88a2-47a3-82e3-32b18a1bc6ec.jpg"},{"is_default":false,"filename":"ngc_6569_2f597094-71e5-4b18-a1f7-9bd62f893afb.jpg"}]}