{"name":"NGC1346","id":1346,"images":[{"filename":"ngc_1346_default.jpg","description":"SDSS image of region near spiral galaxy NGC 1346 and its companion, PGC 13005, overlaid on a DSS background to fill in missing areas","origin_url":"https://cseligman.com/text/atlas/ngc13.htm#1346","is_default":true},{"filename":"ngc_1346_b246fa97-3a6f-40f0-a20f-be73cb1f22c0.jpg","description":"SDSS image of spiral galaxy NGC 1346 and companion, PGC 13005","origin_url":"https://cseligman.com/text/atlas/ngc13.htm#1346","is_default":false},{"filename":"ngc_1346_2573c99a-eea0-4d0e-b8f4-f1c8cb30cd00.jpg","description":"SDSS image of spiral galaxy NGC 1346","origin_url":"https://cseligman.com/text/atlas/ngc13.htm#1346","is_default":false},{"filename":"ngc_1346_8e153867-4d1b-4eee-af01-552aa655f380.jpg","description":"SDSS image of spiral galaxy PGC 13005 and part of its companion, spiral galaxy NGC 1346","origin_url":"https://cseligman.com/text/atlas/ngc13.htm#1346","is_default":false}]}