{"name":"NGC107","id":107,"images":[{"filename":"ngc_107_default.jpg","description":"SDSS image of region near spiral galaxy NGC 107","origin_url":"https://cseligman.com/text/atlas/ngc1.htm#107","is_default":true},{"filename":"ngc107.jpg","description":"SDSS image spiral galaxy of NGC 107","origin_url":"https://cseligman.com/text/atlas/ngc1.htm#107"},{"filename":"ngc107wide.jpg","description":"SDSS image of region near spiral galaxy NGC 107, also showing some PGC objects","origin_url":"https://cseligman.com/text/atlas/ngc1.htm#107"},{"is_default":false,"filename":"ngc_107_b6295e87-4f74-4ad8-b7b0-442e1a66f1e9.jpg"},{"is_default":false,"filename":"ngc_107_5f6e9e4c-1e01-4ecd-9ff2-f03b7d5939df.jpg"}]}