{"name":"NGC1161","id":1161,"images":[{"filename":"ngc_1161_default.jpg","description":"SDSS image of region near lenticular galaxy NGC 1161, also showing NGC 1160","origin_url":"https://cseligman.com/text/atlas/ngc11a.htm#1161","is_default":true},{"filename":"ngc_1161_54b830f6-de00-45e1-a62b-e958cc8b7014.jpg","description":"SDSS image of lenticular galaxy NGC 1161","origin_url":"https://cseligman.com/text/atlas/ngc11a.htm#1161","is_default":false},{"filename":"ngc_1161_3ec8ee5a-1ece-49ec-864a-0578bcb243ac.jpg","description":"HST image of dusty rings surrounding the central core of lenticular galaxy NGC 1161","origin_url":"https://cseligman.com/text/atlas/ngc11a.htm#1161","is_default":false}]}