{"name":"NGC3675","id":3675,"images":[{"filename":"ngc_3675_default.jpg","description":"SDSS image of region near spiral galaxy NGC 3675","origin_url":"https://cseligman.com/text/atlas/ngc36a.htm#3675","is_default":true},{"filename":"ngc_3675_6486f2df-c901-48b6-9111-88538d4bed6b.jpg","description":"Mount Lemmon SkyCenter image of spiral galaxy NGC 3675","origin_url":"https://cseligman.com/text/atlas/ngc36a.htm#3675","is_default":false},{"filename":"ngc_3675_32d7991c-cca5-4243-9405-f2310d5bf22f.jpg","description":"'Raw' HST image of part of spiral galaxy NGC 3675","origin_url":"https://cseligman.com/text/atlas/ngc36a.htm#3675","is_default":false}]}