{"name":"NGC1738","id":1738,"images":[{"filename":"ngc_1738_default.jpg","description":"DSS image of region near spiral galaxies NGC 1738 and NGC 1739","origin_url":"https://cseligman.com/text/atlas/ngc17.htm#1738","is_default":true},{"filename":"ngc_1738_d8764637-2bb5-4e4b-bbbd-39fd635b763b.jpg","description":"DSS image of spiral galaxies NGC 1738 and NGC 1739","origin_url":"https://cseligman.com/text/atlas/ngc17.htm#1738","is_default":false},{"filename":"ngc_1738_3b124075-535e-458c-8385-3cbad0b5c59b.jpg","description":"Raw HST image (a 'preview' of unknown origin and orientation) superimposed on a DSS closeup of spiral galaxies NGC 1738 and NGC 1739","origin_url":"https://cseligman.com/text/atlas/ngc17.htm#1738","is_default":false}]}