{"name":"NGC2008","id":2008,"images":[{"filename":"ngc_2008_default.jpg","description":"DSS image of region near spiral galaxy NGC 2008, also showing NGC 2007","origin_url":"https://cseligman.com/text/atlas/ngc20.htm#2008","is_default":true},{"filename":"ngc2008.jpg","description":"HST image of spiral galaxy NGC 2008","origin_url":"https://cseligman.com/text/atlas/ngc20.htm#2008"},{"filename":"ngc2008hst.jpg","description":"HST image of spiral galaxy NGC 2008","origin_url":"https://cseligman.com/text/atlas/ngc20.htm#2008"},{"is_default":false,"filename":"ngc_2008_66170427-12ac-49cf-a479-df401f2d167b.jpg"},{"is_default":false,"filename":"ngc_2008_e9a0dfa9-91b5-474c-aa24-1b5191b72111.jpg"}]}