{"name":"NGC6769","id":6769,"images":[{"filename":"ngc_6769_default.jpg","description":"ESO image of the triple system known as the Devil's Mask (spiral galaxies NGC 6769 and 6770 and lenticular galaxy NGC 6771), superimposed on a DSS image of the region near the triplet","origin_url":"https://cseligman.com/text/atlas/ngc67a.htm#6769","is_default":true},{"filename":"ngc6769.jpg","description":"ESO image of spiral galaxy NGC 6769","origin_url":"https://cseligman.com/text/atlas/ngc67a.htm#6769"},{"filename":"ngc6769tripleeso.jpg","description":"ESO image of the triple system known as the Devil's Mask: spiral galaxies NGC 6769 and 6770, and lenticular galaxy NGC 6771","origin_url":"https://cseligman.com/text/atlas/ngc67a.htm#6769"},{"is_default":false,"filename":"ngc_6769_12cde402-5652-4fa0-8437-bba3e4136b5e.jpg"},{"is_default":false,"filename":"ngc_6769_3ca7e13a-807c-4ddc-b153-78cd5b9919fe.jpg"}]}