{"name":"NGC1360","id":1360,"images":[{"filename":"ngc_1360_default.jpg","description":"Observatorio Antilhue image of planetary nebula NGC 1360, overlaid on a DSS image of the region near the nebula to fill in missing areas","origin_url":"https://cseligman.com/text/atlas/ngc13a.htm#1360","is_default":true},{"filename":"ngc1360caelum.jpg","description":"Mount Lemmon SkyCenter image of planetary nebula NGC 1360","origin_url":"https://cseligman.com/text/atlas/ngc13a.htm#1360"},{"is_default":false,"filename":"ngc_1360_67213808-931b-45bc-9f78-3f9e9a61746f.jpg"}]}