{"name":"NGC6818","id":6818,"images":[{"filename":"ngc_6818_default.jpg","description":"DSS image of region near planetary nebula NGC 6818","origin_url":"https://cseligman.com/text/atlas/ngc68.htm#6818","is_default":true},{"filename":"ngc6818.jpg","description":"NOAO/DSS image of planetary nebula NGC 6818","origin_url":"https://cseligman.com/text/atlas/ngc68.htm#6818"},{"filename":"ngc6818noao.jpg","description":"NOAO image of planetary nebula NGC 6818","origin_url":"https://cseligman.com/text/atlas/ngc68.htm#6818"},{"filename":"ngc6818hst.jpg","description":"HST image of planetary nebula NGC 6818","origin_url":"https://cseligman.com/text/atlas/ngc68.htm#6818"},{"is_default":false,"filename":"ngc_6818_feff251e-6219-4ced-9a9d-a6d37a7e2b89.jpg"},{"is_default":false,"filename":"ngc_6818_237d0e5e-e77d-48e3-b401-0f95a54445e8.jpg"},{"is_default":false,"filename":"ngc_6818_9437efeb-27f6-476e-a313-0f2c1466991e.jpg"}]}