{"name":"NGC5921","id":5921,"images":[{"filename":"ngc_5921_default.jpg","description":"SDSS image of region near spiral galaxy NGC 5921","origin_url":"https://cseligman.com/text/atlas/ngc59.htm#5921","is_default":true},{"filename":"ngc_5921_fb2befa3-df86-4f84-a624-703cd38684dc.jpg","description":"SDSS image of spiral galaxy NGC 5921","origin_url":"https://cseligman.com/text/atlas/ngc59.htm#5921","is_default":false},{"filename":"ngc_5921_16f17c0f-9901-477d-b70c-a02fd1efb70c.jpg","description":"HST image of part of spiral galaxy NGC 5921","origin_url":"https://cseligman.com/text/atlas/ngc59.htm#5921","is_default":false},{"filename":"ngc_5921_1e954c39-4370-4037-96b8-a5f4871aeb65.jpg","description":"HST image of the bar and nucleus of spiral galaxy NGC 5921","origin_url":"https://cseligman.com/text/atlas/ngc59.htm#5921","is_default":false}]}