{"name":"NGC269","id":269,"images":[{"filename":"ngc_269_default.jpg","description":"DSS image of region near NGC 269, an open cluster in the Small Magellanic Cloud, also showing NGC 265","origin_url":"https://cseligman.com/text/atlas/ngc2a.htm#269","is_default":true},{"filename":"ngc269.jpg","description":"DSS image of NGC 269, an open cluster in the Small Magellanic Cloud","origin_url":"https://cseligman.com/text/atlas/ngc2a.htm#269"},{"is_default":false,"filename":"ngc_269_536221ff-c7b4-41f0-9f38-6a781fdb03f3.jpg"}]}