{"name":"NGC3041","id":3041,"images":[{"filename":"ngc_3041_default.jpg","description":"SDSS image of region near spiral galaxy NGC 3041","origin_url":"https://cseligman.com/text/atlas/ngc30.htm#3041","is_default":true},{"filename":"ngc_3041_7fa80029-92fb-430c-b327-f2e65cf9c8f9.jpg","description":"SDSS image of spiral galaxy NGC 3041","origin_url":"https://cseligman.com/text/atlas/ngc30.htm#3041","is_default":false},{"filename":"ngc_3041_8e37fab5-2b95-4a6e-9d50-3bd6b2c644e5.jpg","description":"HST image of part of spiral galaxy NGC 3041","origin_url":"https://cseligman.com/text/atlas/ngc30.htm#3041","is_default":false}]}