{"name":"NGC1351","id":1351,"images":[{"filename":"ngc_1351_default.jpg","description":"DSS image of region near lenticular galaxy NGC 1351","origin_url":"https://cseligman.com/text/atlas/ngc13a.htm#1351","is_default":true},{"filename":"ngc_1351_4aee5073-7429-4d0f-8e5f-1d9ded16a0e5.jpg","description":"Carnegie-Irvine Galaxy Survey image of lenticular galaxy NGC 1351","origin_url":"https://cseligman.com/text/atlas/ngc13a.htm#1351","is_default":false},{"filename":"ngc_1351_d34caddf-db33-4ded-a025-6877a79ab176.jpg","description":"DSS image of region near spiral galaxy PGC 12952, sometimes called NGC 1351A","origin_url":"https://cseligman.com/text/atlas/ngc13a.htm#1351","is_default":false},{"filename":"ngc_1351_109d911c-9f69-4428-9d94-0f86b5700311.jpg","description":"DSS image of spiral galaxy PGC 12952, sometimes called NGC 1351A","origin_url":"https://cseligman.com/text/atlas/ngc13a.htm#1351","is_default":false}]}