{"name":"NGC4802","id":4802,"images":[{"filename":"ngc_4802_default.jpg","description":"DSS image of region near lenticular galaxy NGC 4802","origin_url":"https://cseligman.com/text/atlas/ngc48.htm#4802","is_default":true},{"filename":"ngc_4802_e0558e57-1389-4810-9872-6419e1f39ced.jpg","description":"PanSTARRS image of region near lenticular galaxy NGC 4802","origin_url":"https://cseligman.com/text/atlas/ngc48.htm#4802","is_default":false},{"filename":"ngc_4802_1fb1bf04-0250-4762-843f-bf3f37973820.jpg","description":"Carnegie-Irvine Galaxy Survey image of lenticular galaxy NGC 4802","origin_url":"https://cseligman.com/text/atlas/ngc48.htm#4802","is_default":false},{"filename":"ngc_4802_5f6f9deb-aad9-4cee-b040-da0388d0b0c3.jpg","description":"Carnegie-Irvine Galaxy Survey image of nucleus of lenticular galaxy NGC 4802","origin_url":"https://cseligman.com/text/atlas/ngc48.htm#4802","is_default":false}]}