{"name":"NGC4108","id":4108,"images":[{"filename":"ngc_4108_default.jpg","description":"SDSS image of region near spiral galaxy NGC 4108, also showing PGC 38343 (which is sometimes called NGC 4108A) and PGC 38461 (which is sometimes called NGC 4108B)","origin_url":"https://cseligman.com/text/atlas/ngc41.htm#4108","is_default":true},{"filename":"ngc_4108_c4298796-c824-4537-8ae2-99aa0625fc58.jpg","description":"SDSS image of spiral galaxy NGC 4108","origin_url":"https://cseligman.com/text/atlas/ngc41.htm#4108","is_default":false},{"filename":"ngc_4108_534f8732-6f6c-478a-b6ab-3fe97801ef61.jpg","description":"SDSS image of region near spiral galaxy PGC 38343, which is sometimes called NGC 4108A, also showing NGC 4108","origin_url":"https://cseligman.com/text/atlas/ngc41.htm#4108","is_default":false},{"filename":"ngc_4108_6de111ca-7e19-473f-a59b-431a87ad398e.jpg","description":"SDSS image of spiral galaxy PGC 38343, which is sometimes called NGC 4108A","origin_url":"https://cseligman.com/text/atlas/ngc41.htm#4108","is_default":false},{"filename":"ngc_4108_5cf9102a-518a-4577-89f1-c06ca1a23a1d.jpg","description":"SDSS image of region near spiral galaxy PGC 38461, which is sometimes called NGC 4108B, also showing NGC 4108","origin_url":"https://cseligman.com/text/atlas/ngc41.htm#4108","is_default":false},{"filename":"ngc_4108_57180a81-6bb7-4a37-b68d-4e20b5ebfd43.jpg","description":"SDSS image of spiral galaxy PGC 38461, which is sometimes called NGC 4108B","origin_url":"https://cseligman.com/text/atlas/ngc41.htm#4108","is_default":false}]}