{"name":"NGC116","id":116,"images":[{"filename":"ngc_116_default.jpg","description":"SDSS image of region near lenticular galaxy PGC 1671, which is usually assumed to be NGC 116","origin_url":"https://cseligman.com/text/atlas/ngc1.htm#116","is_default":true},{"filename":"ngc116.jpg","description":"SDSS image of lenticular galaxy PGC 1671, which is usually assumed to be NGC 116","origin_url":"https://cseligman.com/text/atlas/ngc1.htm#116"},{"filename":"ngc116wide.jpg","description":"SDSS image of region near lenticular galaxy PGC 1671, which is usually assumed to be NGC 116, also showing numerous PGC objects","origin_url":"https://cseligman.com/text/atlas/ngc1.htm#116"},{"filename":"ngc116ferrari.jpg","description":"SDSS image of region between Ferrari's position and PGC 1671, the lenticular galaxy usually presumed to be NGC 116","origin_url":"https://cseligman.com/text/atlas/ngc1.htm#116"},{"filename":"pgc1677.jpg","description":"SDSS image of spiral galaxy PGC 1677, a candidate for NGC 116","origin_url":"https://cseligman.com/text/atlas/ngc1.htm#116"},{"filename":"pgc169989wide.jpg","description":"SDSS image of lenticular galaxy PGC 169989, a candidate for NGC 116","origin_url":"https://cseligman.com/text/atlas/ngc1.htm#116"},{"filename":"pgc169989.jpg","description":"SDSS image of lenticular galaxy PGC 169989, a candidate for NGC 116","origin_url":"https://cseligman.com/text/atlas/ngc1.htm#116"},{"is_default":false,"filename":"ngc_116_5e2d220e-7721-40fe-a525-6a4926ee0fda.jpg"},{"is_default":false,"filename":"ngc_116_b0875de6-04ea-45f7-9cf0-c13b8b5ac118.jpg"},{"is_default":false,"filename":"ngc_116_b47b6a5f-32dd-4ea2-ad88-8014b500a2f1.jpg"},{"is_default":false,"filename":"ngc_116_d808f98c-041f-44c3-9434-7f3792499cac.jpg"},{"is_default":false,"filename":"ngc_116_bee3149b-0b9f-4f0b-889c-b277cfcfa7a9.jpg"},{"is_default":false,"filename":"ngc_116_d26b5f1a-d58d-4f64-b479-8c29f4fd25d8.jpg"}]}