{"name":"NGC14","id":14,"images":[{"filename":"ngc_14_default.jpg","description":"SDSS image of region near irregular galaxy NGC 14, also known as Arp 235","origin_url":"https://cseligman.com/text/atlas/ngc0.htm#14","is_default":true},{"filename":"ngc14.jpg","description":"SDSS image of irregular galaxy NGC 14, also known as Arp 235","origin_url":"https://cseligman.com/text/atlas/ngc0.htm#14"},{"filename":"ngc14hst.jpg","description":"'Raw' HST image of part of irregular galaxy NGC 14, also known as Arp 235","origin_url":"https://cseligman.com/text/atlas/ngc0.htm#14"},{"filename":"ngc14wide.jpg","description":"SDSS image of region near irregular galaxy NGC 14, also known as Arp 235, also showing labels for several other objects","origin_url":"https://cseligman.com/text/atlas/ngc0.htm#14"},{"is_default":false,"filename":"ngc_14_7f7246d4-4270-498c-a668-31a9a1baef49.jpg"},{"is_default":false,"filename":"ngc_14_bbf59057-9641-4c51-bdac-6fd7538dde07.jpg"},{"is_default":false,"filename":"ngc_14_4aa81d3f-72d7-4916-89ce-fff3fc841679.jpg"}]}