{"name":"NGC6752","id":6752,"images":[{"filename":"ngc_6752_default.jpg","description":"ESO image of region near globular cluster NGC 6752","origin_url":"https://cseligman.com/text/atlas/ngc67a.htm#6752","is_default":true},{"filename":"ngc_6752_70c6e5fd-7224-4fd7-a9ea-0c29d6255fea.jpg","description":"ESO image of globular cluster NGC 6752","origin_url":"https://cseligman.com/text/atlas/ngc67a.htm#6752","is_default":false},{"filename":"ngc_6752_64f717b9-10b5-4078-b3db-4113f3af7d41.jpg","description":"HST image of the central core of globular cluster NGC 6752","origin_url":"https://cseligman.com/text/atlas/ngc67a.htm#6752","is_default":false}]}