{"name":"NGC734","id":734,"images":[{"filename":"ngc_734_default.jpg","description":"SDSS image of region near spiral galaxy NGC 734","origin_url":"https://cseligman.com/text/atlas/ngc7.htm#734","is_default":true},{"filename":"ngc_734_145f2191-c4e9-46cd-b69b-36bf974b0742.jpg","description":"SDSS image of spiral galaxy NGC 734","origin_url":"https://cseligman.com/text/atlas/ngc7.htm#734","is_default":false},{"filename":"ngc_734_d555fe10-126f-4bec-a852-b620767b11e9.jpg","description":"SDSS image of region near spiral galaxy PGC 7121, which is not NGC 734, overlaid on a DSS image to cover part of the area otherwise missing (a small area not covered by either image database is noted)","origin_url":"https://cseligman.com/text/atlas/ngc7.htm#734","is_default":false},{"filename":"ngc_734_ac6f27bb-6eb2-48e9-b7c8-b99deeb7548c.jpg","description":"SDSS image of spiral galaxy PGC 7121, which is often misidentified as NGC 734","origin_url":"https://cseligman.com/text/atlas/ngc7.htm#734","is_default":false}]}