{"name":"NGC5256","id":5256,"images":[{"filename":"ngc_5256_default.jpg","description":"SDSS image of region near the double galaxy NGC 5256","origin_url":"https://cseligman.com/text/atlas/ngc52a.htm#5256","is_default":true},{"filename":"ngc5256med.jpg","description":"SDSS image the double galaxy NGC 5256 and the extended remnants of their collision","origin_url":"https://cseligman.com/text/atlas/ngc52a.htm#5256"},{"filename":"ngc5256hstold.jpg","description":"Older HST image the double galaxy NGC 5256 and the extended remnants of their collision","origin_url":"https://cseligman.com/text/atlas/ngc52a.htm#5256"},{"filename":"ngc5256hstmed.jpg","description":"HST image the double galaxy NGC 5256 and the extended remnants of their collision, emphasizing the more spectacular features of the collision","origin_url":"https://cseligman.com/text/atlas/ngc52a.htm#5256"},{"filename":"ngc5256hst.jpg","description":"HST image of the central portion of NGC 5256","origin_url":"https://cseligman.com/text/atlas/ngc52a.htm#5256"},{"filename":"ngc5256hstlabel.jpg","description":"HST image of the central portion of NGC 5256","origin_url":"https://cseligman.com/text/atlas/ngc52a.htm#5256"},{"filename":"ngc5256hstclose.jpg","description":"2017 HST image of the pair of colliding galaxies which comprise NGC 5256","origin_url":"https://cseligman.com/text/atlas/ngc52a.htm#5256"},{"filename":"ngc5256.2008.jpg","description":"2008 HST image of the pair of colliding galaxies which comprise NGC 5256","origin_url":"https://cseligman.com/text/atlas/ngc52a.htm#5256"},{"is_default":false,"filename":"ngc_5256_783782b1-244f-4dc7-a901-6976c9c76b52.jpg"},{"is_default":false,"filename":"ngc_5256_08640a8b-09b1-4cab-9059-ca2ac3fc293c.jpg"},{"is_default":false,"filename":"ngc_5256_fa26c439-9492-46e3-ba7b-6238c59ee455.jpg"},{"is_default":false,"filename":"ngc_5256_cbb14829-b794-4f22-95d6-a61c963588d7.jpg"},{"is_default":false,"filename":"ngc_5256_0f2fe8f7-eb1e-40d9-8039-7d3e24dbcc0d.jpg"},{"is_default":false,"filename":"ngc_5256_4046b943-503c-415b-9841-dd8e479b7431.jpg"},{"is_default":false,"filename":"ngc_5256_80825ecf-9708-4e2b-bc9e-6014852edd69.jpg"}]}