{"name":"NGC6543","id":6543,"images":[{"filename":"ngc_6543_default.jpg","description":"DSS image of the region near planetary nebula NGC 6543, the Cat's Eye Nebula","origin_url":"https://cseligman.com/text/atlas/ngc65.htm#6543","is_default":true},{"filename":"ngc_6543_5cf95431-cd26-4db8-8d95-84b1a9c0df3f.jpg","description":"Nordic Optical Telescope image of planetary nebula NGC 6543, the Cat's Eye Nebula, and its outer halo","origin_url":"https://cseligman.com/text/atlas/ngc65.htm#6543","is_default":false},{"filename":"ngc_6543_7e20c65a-016c-436d-8ea8-94fe15e6d9a3.jpg","description":"HST image of the central portion of planetary nebula NGC 6543, the Cat's Eye Nebula","origin_url":"https://cseligman.com/text/atlas/ngc65.htm#6543","is_default":false},{"filename":"ngc_6543_1c359dbb-57cb-4707-bacb-ed07773be296.jpg","description":"Composite GALEX/HST image of the central portion of planetary nebula NGC 6543, the Cat's Eye Nebula","origin_url":"https://cseligman.com/text/atlas/ngc65.htm#6543","is_default":false},{"filename":"ngc_6543_84c16dd8-d5c4-4f6f-ab99-a2d2a3a4930e.jpg","description":"HST image of the central portion of planetary nebula NGC 6543, the Cat's Eye Nebula","origin_url":"https://cseligman.com/text/atlas/ngc65.htm#6543","is_default":false}]}