{"name":"NGC1533","id":1533,"images":[{"filename":"ngc_1533_default.jpg","description":"DSS image of region near lenticular galaxy NGC 1533","origin_url":"https://cseligman.com/text/atlas/ngc15.htm#1533","is_default":true},{"filename":"ngc_1533_437b7fe8-9d06-4a9b-ae47-73c142c7f502.jpg","description":"Carnegie-Irvine Galaxy Survey image of lenticular galaxy NGC 1533","origin_url":"https://cseligman.com/text/atlas/ngc15.htm#1533","is_default":false},{"filename":"ngc_1533_bc15032f-c086-4f92-978f-228a59a9fbb8.jpg","description":"HST image of part of lenticular galaxy NGC 1533","origin_url":"https://cseligman.com/text/atlas/ngc15.htm#1533","is_default":false}]}