{"name":"NGC6348","id":6348,"images":[{"filename":"ngc_6348_default.jpg","description":"SDSS image of region near lenticular galaxy NGC 6348, with a DSS image replacing a region obscured by glare, also showing NGC 6350","origin_url":"https://cseligman.com/text/atlas/ngc63.htm#6348","is_default":true},{"filename":"ngc6348.jpg","description":"SDSS image of lenticular galaxy NGC 6348","origin_url":"https://cseligman.com/text/atlas/ngc63.htm#6348"},{"is_default":false,"filename":"ngc_6348_61891bae-e2a3-4a00-a59b-64864530d077.jpg"}]}