{"name":"NGC3922","id":3922,"images":[{"filename":"ngc_3922_default.jpg","description":"SDSS image of region near lenticular galaxy NGC 3922, which is a duplicate observation of NGC 3924","origin_url":"https://cseligman.com/text/atlas/ngc39.htm#3922","is_default":true},{"filename":"ngc_3922_f1491c77-ebe1-4ff9-af9a-cbd7a5d2baf6.jpg","description":"SDSS image of lenticular galaxy NGC 3922, which is a duplicate observation of NGC 3924","origin_url":"https://cseligman.com/text/atlas/ngc39.htm#3922","is_default":false}]}