{"name":"IC1923","id":1923,"images":[{"filename":"ic_1923_default.jpg","description":"DSS image of region near galaxy PGC 465294 and foreground star J0324518-503321, which in one way or another comprise IC 1923","origin_url":"https://cseligman.com/text/atlas/ic19.htm#ic1923","is_default":true},{"filename":"ic1923.jpg","description":"DSS image of galaxy PGC 465294 and foreground star J0324518-503321, which in one way or another comprise IC 1923","origin_url":"https://cseligman.com/text/atlas/ic19.htm#ic1923"},{"is_default":false,"filename":"ic_1923_9d8e4efd-125a-401b-8544-a8050c97e3c5.jpg"}]}