{"name":"IC3335","id":3335,"images":[{"filename":"ic_3335_default.jpg","description":"SDSS image of lenticular galaxy IC 3335, also showing lenticular galaxy PGC 3089429, which is sometimes mistaken for IC 3335","origin_url":"https://cseligman.com/text/atlas/ic33.htm#ic3335","is_default":true},{"filename":"ic_3335_1f48d852-e919-4392-8f77-8430180ff68d.jpg","description":"SDSS image of region near lenticular galaxy IC 3335, also showing lenticular galaxy PGC 3089429, which is sometimes mistaken for IC 3335","origin_url":"https://cseligman.com/text/atlas/ic33.htm#ic3335","is_default":false}]}