{"name":"IC385","id":385,"images":[{"filename":"ic_385_default.jpg","description":"DSS image of region near lenticular galaxy IC 385","origin_url":"https://cseligman.com/text/atlas/ic3a.htm#ic385","is_default":true},{"filename":"ic385.jpg","description":"DSS image of lenticular galaxy IC 385","origin_url":"https://cseligman.com/text/atlas/ic3a.htm#ic385"},{"filename":"ic385pstarrs.jpg","description":"PanSTARRS image of the nucleus of lenticular galaxy IC 385","origin_url":"https://cseligman.com/text/atlas/ic3a.htm#ic385"},{"is_default":false,"filename":"ic_385_1485749d-1602-4929-9f09-b9d0f7722fef.jpg"},{"is_default":false,"filename":"ic_385_8d08007b-ba8d-44b3-877a-b1c89d6f7ecb.jpg"}]}