{"name":"IC345","id":345,"images":[{"filename":"ic_345_default.jpg","description":"DSS image of region near lenticular galaxy IC 345","origin_url":"https://cseligman.com/text/atlas/ic3.htm#ic345","is_default":true},{"filename":"ic_345_873b8322-75c4-46a6-a82c-af78a733b651.jpg","description":"DSS image of lenticular galaxy IC 345","origin_url":"https://cseligman.com/text/atlas/ic3.htm#ic345","is_default":false},{"filename":"ic_345_36fce0a3-88a7-4d6a-a7aa-4f26206e62c5.jpg","description":"PanSTARRS image of nucleus of lenticular galaxy IC 345","origin_url":"https://cseligman.com/text/atlas/ic3.htm#ic345","is_default":false}]}