{"name":"IC4248","id":4248,"images":[{"filename":"ic_4248_default.jpg","description":"DSS image of region near spiral galaxy IC 4248","origin_url":"https://cseligman.com/text/atlas/ic42.htm#ic4248","is_default":true},{"filename":"ic4248.jpg","description":"DSS image of spiral galaxy IC 4248","origin_url":"https://cseligman.com/text/atlas/ic42.htm#ic4248"},{"filename":"ic4248eso.jpg","description":"ESO image of spiral galaxy IC 4248","origin_url":"https://cseligman.com/text/atlas/ic42.htm#ic4248"},{"is_default":false,"filename":"ic_4248_f0aa75de-91dc-4787-9e18-89e525895067.jpg"},{"is_default":false,"filename":"ic_4248_5f570f08-49ae-4671-a7d1-db168ac94ad9.jpg"}]}