{"name":"IC656","id":656,"images":[{"filename":"ic_656_default.jpg","description":"SDSS image of the three galactic stars and spiral galaxy that comprise IC 656","origin_url":"https://cseligman.com/text/atlas/ic6a.htm#ic656","is_default":true},{"filename":"ic656wide.jpg","description":"SDSS image of region near the three galactic stars and spiral galaxy that comprise IC 656; also shown is the elliptical galaxy that is almost certainly NGC 3457","origin_url":"https://cseligman.com/text/atlas/ic6a.htm#ic656"},{"is_default":false,"filename":"ic_656_3a669cef-9ec0-480e-aa71-a3e58bb6ec9e.jpg"}]}