{"name":"IC226","id":226,"images":[{"filename":"ic_226_default.jpg","description":"DSS image of region near spiral galaxy IC 226, also showing IC 227","origin_url":"https://cseligman.com/text/atlas/ic2.htm#ic226","is_default":true},{"filename":"ic226.jpg","description":"DSS image of spiral galaxy IC 226","origin_url":"https://cseligman.com/text/atlas/ic2.htm#ic226"},{"filename":"ic226pstarrs.jpg","description":"DSS image of spiral galaxy IC 226","origin_url":"https://cseligman.com/text/atlas/ic2.htm#ic226"},{"is_default":false,"filename":"ic_226_53598610-200d-41f2-bd24-a1261120d6df.jpg"},{"is_default":false,"filename":"ic_226_233a31c1-2be4-4c1e-adab-957651d3b616.jpg"}]}