{"name":"IC245","id":245,"images":[{"filename":"ic_245_default.jpg","description":"DSS image of region near spiral galaxy IC 245","origin_url":"https://cseligman.com/text/atlas/ic2.htm#ic245","is_default":true},{"filename":"ic_245_8106cacf-6052-4f8d-8113-8c89568c772a.jpg","description":"DSS image of spiral galaxy IC 245","origin_url":"https://cseligman.com/text/atlas/ic2.htm#ic245","is_default":false},{"filename":"ic_245_71696475-5282-427d-89d4-af5008631271.jpg","description":"PanSTARRS image of spiral galaxy IC 245","origin_url":"https://cseligman.com/text/atlas/ic2.htm#ic245","is_default":false}]}