{"name":"IC3303","id":3303,"images":[{"filename":"ic_3303_default.jpg","description":"SDSS image of dwarf lenticular galaxy IC 3303","origin_url":"https://cseligman.com/text/atlas/ic33.htm#ic3303","is_default":true},{"filename":"ic3303wide.jpg","description":"SDSS image of region near dwarf lenticular galaxy IC 3303, also showing part of spiral galaxy NGC 4388","origin_url":"https://cseligman.com/text/atlas/ic33.htm#ic3303"},{"is_default":false,"filename":"ic_3303_8833dd1b-5573-4f01-b4c4-8eddce4ead82.jpg"}]}