{"name":"IC344","id":344,"images":[{"filename":"ic_344_default.jpg","description":"DSS image of region near spiral galaxy IC 344","origin_url":"https://cseligman.com/text/atlas/ic3.htm#ic344","is_default":true},{"filename":"ic_344_d2fd80d7-8247-4d58-9ced-f662a7d4815f.jpg","description":"DSS image of spiral galaxy IC 344","origin_url":"https://cseligman.com/text/atlas/ic3.htm#ic344","is_default":false},{"filename":"ic_344_bc837246-80b4-4d36-9230-e767f06b26f4.jpg","description":"PanSTARRS image of spiral galaxy IC 344","origin_url":"https://cseligman.com/text/atlas/ic3.htm#ic344","is_default":false}]}