{"name":"IC4248","id":4248,"images":[{"filename":"ic_4248_default.jpg","description":"DSS image of region near spiral galaxy IC 4248","origin_url":"https://cseligman.com/text/atlas/ic42.htm#ic4248","is_default":true},{"filename":"ic_4248_7a0473cb-c195-4100-a792-21a3f8c2e63b.jpg","description":"DSS image of spiral galaxy IC 4248","origin_url":"https://cseligman.com/text/atlas/ic42.htm#ic4248","is_default":false},{"filename":"ic_4248_6ecb187b-6a7d-4782-b7fe-9564ddf9ead0.jpg","description":"ESO image of spiral galaxy IC 4248","origin_url":"https://cseligman.com/text/atlas/ic42.htm#ic4248","is_default":false}]}