{"name":"IC552","id":552,"images":[{"filename":"ic_552_default.jpg","description":"SDSS image of region near lenticular galaxy IC 552","origin_url":"https://cseligman.com/text/atlas/ic5a.htm#ic552","is_default":true},{"filename":"ic_552_b0fd43ea-5c71-4767-9afb-de957b48b89e.jpg","description":"SDSS image of lenticular galaxy IC 552","origin_url":"https://cseligman.com/text/atlas/ic5a.htm#ic552","is_default":false},{"filename":"ic_552_280e44cb-f171-445f-b963-0be8e61d3a0e.jpg","description":"SDSS image of spiral galaxy PGC 27682, a possible companion of IC 552","origin_url":"https://cseligman.com/text/atlas/ic5a.htm#ic552","is_default":false},{"filename":"ic_552_18703f4c-a5d4-4567-bdce-31392755784e.jpg","description":"DECaLS image of spiral galaxy PGC 27682, a possible companion of IC 552","origin_url":"https://cseligman.com/text/atlas/ic5a.htm#ic552","is_default":false}]}