{"name":"IC688","id":688,"images":[{"filename":"ic_688_default.jpg","description":"SDSS image of spiral galaxy IC 688","origin_url":"https://cseligman.com/text/atlas/ic6a.htm#ic688","is_default":true},{"filename":"ic_688_2f049791-9afa-4dec-9274-b480dcb0b88d.jpg","description":"SDSS image of region near spiral galaxy IC 688","origin_url":"https://cseligman.com/text/atlas/ic6a.htm#ic688","is_default":false},{"filename":"ic_688_6692877c-d292-4192-8490-e04a1456bbcc.jpg","description":"SDSS image of J2000 112424.2-094735, an elliptical galaxy sometimes misidentified as IC 688","origin_url":"https://cseligman.com/text/atlas/ic6a.htm#ic688","is_default":false},{"filename":"ic_688_076aa0a4-5d87-476e-97b8-b2114572a2cd.jpg","description":"SDSS image of region near J2000 112424.2-094735, an elliptical galaxy sometimes misidentified as IC 688","origin_url":"https://cseligman.com/text/atlas/ic6a.htm#ic688","is_default":false}]}