{"name":"IC738","id":738,"images":[{"filename":"ic_738_default.jpg","description":"DSS image of region near spiral galaxy IC 738","origin_url":"https://cseligman.com/text/atlas/ic7.htm#ic738","is_default":true},{"filename":"ic738.jpg","description":"DSS image of spiral galaxy IC 738","origin_url":"https://cseligman.com/text/atlas/ic7.htm#ic738"},{"filename":"ic738pstarr.jpg","description":"PanSTARRS image of spiral galaxy IC 738","origin_url":"https://cseligman.com/text/atlas/ic7.htm#ic738"},{"filename":"pgc2816780.jpg","description":"DSS image of the pair of interacting galaxies listed as PGC 2816780, which is sometimes misidentified as IC 738","origin_url":"https://cseligman.com/text/atlas/ic7.htm#ic738"},{"filename":"pgc2816780pstarr.jpg","description":"PanSTARRS image of the pair of interacting galaxies listed as PGC 2816780, which is sometimes misidentified as IC 738","origin_url":"https://cseligman.com/text/atlas/ic7.htm#ic738"},{"is_default":false,"filename":"ic_738_ca7cbd85-aa5b-4d60-8a48-86dd73b937e6.jpg"},{"is_default":false,"filename":"ic_738_913b609a-3fa5-4f89-bc65-fcee1b586489.jpg"},{"is_default":false,"filename":"ic_738_19ce5a1e-b547-40c6-84f6-e1ffa9ea0f47.jpg"},{"is_default":false,"filename":"ic_738_2c50adaf-bdff-4681-82ba-08f549e0eae0.jpg"}]}